mrgeppetto/__init__.py
mrgeppetto-0.0.1.dist-info/METADATA
mrgeppetto-0.0.1.dist-info/WHEEL
mrgeppetto-0.0.1.dist-info/top_level.txt
mrgeppetto-0.0.1.dist-info/RECORD
